odoo/addons/beesdoo_shift/README.rst
odoo/addons/beesdoo_shift/__init__.py
odoo/addons/beesdoo_shift/__manifest__.py
odoo/addons/beesdoo_shift/data/cron.xml
odoo/addons/beesdoo_shift/data/mail_template.xml
odoo/addons/beesdoo_shift/data/system_parameter.xml
odoo/addons/beesdoo_shift/demo/exempt_reason.xml
odoo/addons/beesdoo_shift/demo/templates.xml
odoo/addons/beesdoo_shift/demo/workers.xml
odoo/addons/beesdoo_shift/i18n/beesdoo_shift.pot
odoo/addons/beesdoo_shift/i18n/en_US.po
odoo/addons/beesdoo_shift/i18n/fr.po
odoo/addons/beesdoo_shift/i18n/nl.po
odoo/addons/beesdoo_shift/migrations/12.0.1.1.0/post-migrate.py
odoo/addons/beesdoo_shift/migrations/12.0.2.1.1/pre-migrate.py
odoo/addons/beesdoo_shift/models/__init__.py
odoo/addons/beesdoo_shift/models/cooperative_status.py
odoo/addons/beesdoo_shift/models/planning.py
odoo/addons/beesdoo_shift/models/res_config_settings.py
odoo/addons/beesdoo_shift/models/res_partner.py
odoo/addons/beesdoo_shift/models/task.py
odoo/addons/beesdoo_shift/readme/CONFIGURE.rst
odoo/addons/beesdoo_shift/readme/CONTRIBUTORS.rst
odoo/addons/beesdoo_shift/readme/DESCRIPTION.rst
odoo/addons/beesdoo_shift/readme/HISTORY.rst
odoo/addons/beesdoo_shift/security/group.xml
odoo/addons/beesdoo_shift/security/ir.model.access.csv
odoo/addons/beesdoo_shift/static/description/icon.png
odoo/addons/beesdoo_shift/static/description/index.html
odoo/addons/beesdoo_shift/tests/__init__.py
odoo/addons/beesdoo_shift/tests/test_beesdoo_shift.py
odoo/addons/beesdoo_shift/views/cooperative_status.xml
odoo/addons/beesdoo_shift/views/exempt_reason.xml
odoo/addons/beesdoo_shift/views/menu.xml
odoo/addons/beesdoo_shift/views/planning.xml
odoo/addons/beesdoo_shift/views/res_config_settings_view.xml
odoo/addons/beesdoo_shift/views/task.xml
odoo/addons/beesdoo_shift/views/task_template.xml
odoo/addons/beesdoo_shift/wizard/__init__.py
odoo/addons/beesdoo_shift/wizard/assign_super_coop.py
odoo/addons/beesdoo_shift/wizard/assign_super_coop.xml
odoo12_addon_beesdoo_shift-12.0.4.0.0.dist-info/METADATA
odoo12_addon_beesdoo_shift-12.0.4.0.0.dist-info/WHEEL
odoo12_addon_beesdoo_shift-12.0.4.0.0.dist-info/top_level.txt
odoo12_addon_beesdoo_shift-12.0.4.0.0.dist-info/RECORD
